PythonPSI/__init__.py
PythonPSI/about.txt
PythonPSI/api.py
PythonPSI/main.py
PythonPSI/utils/data.py
PythonPSI/utils/version.py
PythonPSI-1.9.2.dist-info/LICENSE
PythonPSI-1.9.2.dist-info/METADATA
PythonPSI-1.9.2.dist-info/WHEEL
PythonPSI-1.9.2.dist-info/entry_points.txt
PythonPSI-1.9.2.dist-info/top_level.txt
PythonPSI-1.9.2.dist-info/RECORD
