Metadata-Version: 2.1
Name: PythonPSI
Version: 1.9.2
Summary: CLI + API for Google PageSpeed Insights
Home-page: https://github.com/prakhargurunani/PyPSI
Author: Prakhar Gurunani
Author-email: prakhargurunani@gmail.com
License: UNKNOWN
Download-URL: https://github.com/prakhargurunani/PyPSI/archive/main.zip
Keywords: cli,google,python,seo,page-speed-insights,performance,google-apis
Platform: UNKNOWN
Classifier: Development Status :: 5 - Production/Stable
Classifier: Intended Audience :: Developers
Classifier: Topic :: Software Development :: Build Tools
Classifier: License :: OSI Approved :: MIT License
Classifier: Programming Language :: Python :: 3
Classifier: Programming Language :: Python :: 3.5
Classifier: Programming Language :: Python :: 3.6
Classifier: Programming Language :: Python :: 3.7
Classifier: Programming Language :: Python :: 3.8
Classifier: Programming Language :: Python :: 3.9
Classifier: Programming Language :: Python :: 3 :: Only
Requires-Python: >=3.5, <4
License-File: LICENSE
Requires-Dist: click
Requires-Dist: requests
